pyfortianalyzer/__init__.py
pyfortianalyzer/core/__init__.py
pyfortianalyzer/core/api.py
pyfortianalyzer/core/fortianalyzer.py
pyfortianalyzer/models/__init__.py
pyfortianalyzer/models/adoms.py
pyfortianalyzer/models/fortigates.py
pyfortianalyzer/models/system.py
pyfortianalyzer-2.0.0.dist-info/LICENSE
pyfortianalyzer-2.0.0.dist-info/METADATA
pyfortianalyzer-2.0.0.dist-info/WHEEL
pyfortianalyzer-2.0.0.dist-info/top_level.txt
pyfortianalyzer-2.0.0.dist-info/RECORD
