Metadata-Version: 2.1
Name: pyfortianalyzer
Version: 2.0.0
Summary: Python API client library for Fortinet's FortiAnalyzer.
Home-page: https://github.com/BESTSELLER/pyfortianalyzer
Author: Rasmus Thing
Author-email: rasmus.thing@bestseller.com
License: Apache2
Keywords: fortinet,fortianalyzer
Classifier: Intended Audience :: Developers
Classifier: Programming Language :: Python :: 3.8
Classifier: Programming Language :: Python :: 3.9
Classifier: Programming Language :: Python :: 3.10
Classifier: Programming Language :: Python :: 3.11
Classifier: Programming Language :: Python :: 3.12
Requires-Python: >=3.8, <4
License-File: LICENSE
Requires-Dist: requests <3.0,>=2.20.0
